{
  "userId": "b88958bd-d902-4157-9b38-b3d09168f120",
  "onboardingComplete": false,
  "currentStep": "home",
  "personaStage": "q1",
  "goalStage": "choice",
  "budgetStage": "digest",
  "personaAnswers": {},
  "goal": null,
  "budgetOverrides": {},
  "budgetStyle": null,
  "bufferAmount": 4000,
  "bufferRemaining": 4000,
  "products": [],
  "preferences": [],
  "spendRatings": [],
  "nudges": [],
  "activeFlow": null,
  "lastActiveAt": "2026-03-13T07:46:15.244Z",
  "createdAt": "2026-03-13T07:46:15.242Z"
}