{
  "userId": "025dff41-5351-49b9-b11b-d5906c014325",
  "onboardingComplete": false,
  "currentStep": "goal",
  "personaStage": "q1",
  "goalStage": "choice",
  "budgetStage": "digest",
  "personaAnswers": {},
  "goal": null,
  "budgetOverrides": {},
  "budgetStyle": null,
  "bufferAmount": 4000,
  "bufferRemaining": 4000,
  "products": [],
  "preferences": [],
  "spendRatings": [
    {
      "txnId": "rtxn-2025-06-07-591",
      "category": "Other / Uncategorized",
      "amount": 591,
      "rating": "worth",
      "timeOfDay": "morning",
      "ratedAt": "2026-03-13T08:18:01.308Z"
    }
  ],
  "nudges": [],
  "activeFlow": null,
  "lastActiveAt": "2026-03-13T08:26:04.674Z",
  "createdAt": "2026-03-13T08:08:37.622Z"
}